hbn_postprocessing/__init__.py
hbn_postprocessing/file_count.py
hbn_postprocessing/html.py
hbn_postprocessing/jobs.py
hbn_postprocessing/main.py
hbn_postprocessing/motion.py
hbn_postprocessing/utils.py
hbn_postprocessing-0.4.0.dist-info/METADATA
hbn_postprocessing-0.4.0.dist-info/WHEEL
hbn_postprocessing-0.4.0.dist-info/entry_points.txt
hbn_postprocessing-0.4.0.dist-info/RECORD
