Metadata-Version: 2.1
Name: hbn-postprocessing
Version: 0.4.0
Summary: Postprocessing workflow for HBN data
Author: Tristan Kuehn
Author-email: tkuehn@uwo.ca
Requires-Python: >=3.8,<3.12
Classifier: Programming Language :: Python :: 3
Classifier: Programming Language :: Python :: 3.8
Classifier: Programming Language :: Python :: 3.9
Classifier: Programming Language :: Python :: 3.10
Classifier: Programming Language :: Python :: 3.11
Requires-Dist: numpy (>=1.21.4,<2.0.0)
Requires-Dist: pandas (>=1.3.5,<2.0.0)
